cloudhouse_guardian/Account.py
cloudhouse_guardian/BaseObject.py
cloudhouse_guardian/ChangeRequest.py
cloudhouse_guardian/ChangeRequestList.py
cloudhouse_guardian/ConnectionManager.py
cloudhouse_guardian/ConnectionManagerGroup.py
cloudhouse_guardian/ConnectionManagerGroupList.py
cloudhouse_guardian/ConnectionManagerList.py
cloudhouse_guardian/Environment.py
cloudhouse_guardian/EnvironmentList.py
cloudhouse_guardian/Event.py
cloudhouse_guardian/EventAction.py
cloudhouse_guardian/EventActionList.py
cloudhouse_guardian/EventList.py
cloudhouse_guardian/EventVariables.py
cloudhouse_guardian/ExternalEvent.py
cloudhouse_guardian/Incident.py
cloudhouse_guardian/IncidentList.py
cloudhouse_guardian/Job.py
cloudhouse_guardian/JobList.py
cloudhouse_guardian/MediumType.py
cloudhouse_guardian/Node.py
cloudhouse_guardian/NodeGroup.py
cloudhouse_guardian/NodeGroupList.py
cloudhouse_guardian/NodeGroupUser.py
cloudhouse_guardian/NodeGroupUserList.py
cloudhouse_guardian/NodeList.py
cloudhouse_guardian/NodeMediumInfo.py
cloudhouse_guardian/NodeScan.py
cloudhouse_guardian/NodeScanList.py
cloudhouse_guardian/NodeType.py
cloudhouse_guardian/OperatingSystem.py
cloudhouse_guardian/OperatingSystemFamily.py
cloudhouse_guardian/OperatingSystemFamilyList.py
cloudhouse_guardian/OperatingSystemList.py
cloudhouse_guardian/Pluggable.py
cloudhouse_guardian/PluggableList.py
cloudhouse_guardian/Policy.py
cloudhouse_guardian/PolicyList.py
cloudhouse_guardian/ScheduledJob.py
cloudhouse_guardian/ScheduledJobList.py
cloudhouse_guardian/SystemMetric.py
cloudhouse_guardian/SystemMetricList.py
cloudhouse_guardian/User.py
cloudhouse_guardian/UserList.py
cloudhouse_guardian/Version.py
cloudhouse_guardian/__init__.py
cloudhouse_guardian-0.0.18.dist-info/METADATA
cloudhouse_guardian-0.0.18.dist-info/WHEEL
cloudhouse_guardian-0.0.18.dist-info/top_level.txt
cloudhouse_guardian-0.0.18.dist-info/RECORD
